pyleetspeak/InversionCamouflage.py
pyleetspeak/LeetSpeaker.py
pyleetspeak/Leet_NER_generator.py
pyleetspeak/PunctuationCamouflage.py
pyleetspeak/WordCamouflage_Augmenter.py
pyleetspeak/__init__.py
pyleetspeak/format_converter.py
pyleetspeak/modes.py
pyleetspeak/spacy_ner_formal_test.py
scripts/__init__.py
scripts/pyleetspeak.py
tests/__init__.py
tests/test_leetspeaker.py
pyleetspeak-0.3.9.dist-info/LICENSE
pyleetspeak-0.3.9.dist-info/METADATA
pyleetspeak-0.3.9.dist-info/WHEEL
pyleetspeak-0.3.9.dist-info/top_level.txt
pyleetspeak-0.3.9.dist-info/RECORD
