Metadata-Version: 2.1
Name: pyleetspeak
Version: 0.3.9
Summary: Transform casual text into a leetspeak and word camouflage version.
Home-page: https://github.com/Huertas97/pyleetspeak
Author: Álvaro Huertas García
Author-email: <alvaro.huertas.garcia@alumnos.upm.es>
License: UNKNOWN
Keywords: leetspeak,woord camouflage,content evasion,information disorders,social media,data augmentation
Platform: UNKNOWN
Classifier: Development Status :: 1 - Planning
Classifier: Intended Audience :: Developers
Classifier: Programming Language :: Python :: 3
Classifier: Operating System :: Unix
License-File: LICENSE
Requires-Dist: codetiming
Requires-Dist: keybert
Requires-Dist: matplotlib
Requires-Dist: nltk (==3.6.7)
Requires-Dist: numpy (==1.21.5)
Requires-Dist: Pyphen
Requires-Dist: scikit-learn (==1.0.2)
Requires-Dist: setuptools
Requires-Dist: spacy (==3.4.3)
Requires-Dist: tqdm
Requires-Dist: Unidecode
Requires-Dist: yake (==0.4.8)
